custom_telegraph/__init__.py
custom_telegraph/telegraph_account.py
custom_telegraph/types/__init__.py
custom_telegraph/types/account.py
custom_telegraph/types/base.py
custom_telegraph/types/page.py
custom_telegraph/types/page_list.py
custom_telegraph-0.1.0.dist-info/METADATA
custom_telegraph-0.1.0.dist-info/WHEEL
custom_telegraph-0.1.0.dist-info/top_level.txt
custom_telegraph-0.1.0.dist-info/RECORD
