Metadata-Version: 2.1
Name: custom_telegraph
Version: 0.1.0
Summary: A library adds dots annotation to telegraph library
Author: BeadierMitten49
Classifier: Programming Language :: Python :: 3
Classifier: Operating System :: OS Independent
Requires-Python: >=3.7
Requires-Dist: telegraph
